kececifractals/__init__.py
kececifractals/_version.py
kececifractals/kececifractals.py
kececifractals-0.2.2.dist-info/licenses/LICENSE
kececifractals-0.2.2.dist-info/METADATA
kececifractals-0.2.2.dist-info/WHEEL
kececifractals-0.2.2.dist-info/top_level.txt
kececifractals-0.2.2.dist-info/RECORD
