Metadata-Version: 2.4
Name: kececifractals
Version: 0.2.2
Summary: Keçeci Fractals: Keçeci-style circle fractal.
Home-page: https://github.com/WhiteSymmetry/kececifractals
Author: Mehmet Keçeci
Author-email: Mehmet Keçeci <mkececi@yaani.com>
Maintainer: Mehmet Keçeci
Maintainer-email: bilginomi@yaani.com
License:                     GNU AFFERO GENERAL PUBLIC LICENSE
Project-URL: Homepage, https://github.com/WhiteSymmetry/kececifractals
Project-URL: Bug Tracker, https://github.com/WhiteSymmetry/kececifractals/issues
Classifier: Programming Language :: Python :: 3
Classifier: Operating System :: OS Independent
Classifier: Intended Audience :: Science/Research
Classifier: Topic :: Scientific/Engineering :: Visualization
Requires-Python: >=3.11
License-File: LICENSE
Requires-Dist: kececilayout
Requires-Dist: networkx
Requires-Dist: matplotlib
Requires-Dist: numpy
Provides-Extra: test
Requires-Dist: pytest; extra == "test"
Requires-Dist: pytest-cov; extra == "test"
Requires-Dist: pytest-mock; extra == "test"
Requires-Dist: ruff; extra == "test"
Requires-Dist: kececilayout; extra == "test"
Requires-Dist: networkx; extra == "test"
Requires-Dist: matplotlib; extra == "test"
Requires-Dist: numpy; extra == "test"
Dynamic: author
Dynamic: home-page
Dynamic: license-file
Dynamic: maintainer
Dynamic: maintainer-email
Dynamic: requires-python
